AUTHORS
ChangeLog
LICENSE
README.md
requirements.txt
setup.cfg
setup.py
missing_license/__init__.py
missing_license.egg-info/PKG-INFO
missing_license.egg-info/SOURCES.txt
missing_license.egg-info/dependency_links.txt
missing_license.egg-info/entry_points.txt
missing_license.egg-info/not-zip-safe
missing_license.egg-info/requires.txt
missing_license.egg-info/top_level.txt