Metadata-Version: 1.1
Name: missing-license
Version: 375f5f5
Summary: Let GitHub users know if their projects are missing a license.
Home-page: UNKNOWN
Author: Liam Middlebrook
Author-email: liammiddlebrook@gmail.com
License: GPLv3+
Keywords: license
Platform: UNKNOWN
Classifier: Natural Language :: English
Classifier: Operating System :: POSIX :: Linux
Classifier: Programming Language :: Python :: 2.7
